black_langcube/__init__.py
black_langcube/process.py
black_langcube/data_structures/__init__.py
black_langcube/data_structures/data_structures.py
black_langcube/examples/basic_workflow.py
black_langcube/examples/custom_llm_node.py
black_langcube/examples/data_structures_example.py
black_langcube/examples/dummy_implementations.py
black_langcube/examples/library_usage.py
black_langcube/examples/translation_workflow.py
black_langcube/format_instructions/__init__.py
black_langcube/format_instructions/analyst_format.py
black_langcube/graf/__init__.py
black_langcube/graf/graf1.py
black_langcube/graf/graf2.py
black_langcube/graf/graf3.py
black_langcube/graf/graf4.py
black_langcube/graf/graf5.py
black_langcube/graf/graph_base.py
black_langcube/graf/subgrafs/__init__.py
black_langcube/graf/subgrafs/message_translator_subgraf.py
black_langcube/graf/subgrafs/translator_en_subgraf.py
black_langcube/graf/subgrafs/translator_usr_subgraf.py
black_langcube/helper_modules/__init__.py
black_langcube/helper_modules/calculate_duration.py
black_langcube/helper_modules/escaping.py
black_langcube/helper_modules/get_basegraph_classes.py
black_langcube/helper_modules/get_result_from_graph_outputs.py
black_langcube/helper_modules/submodules.py
black_langcube/helper_modules/helper_nodes/__init__.py
black_langcube/helper_modules/helper_nodes/graph1_sample.py
black_langcube/helper_modules/helper_nodes/graph5_sample.py
black_langcube/helper_modules/helper_nodes/subgraphs/__init__.py
black_langcube/helper_modules/token_counter/__init__.py
black_langcube/helper_modules/token_counter/generic_counter_node.py
black_langcube/helper_modules/token_counter/token_costs_count.py
black_langcube/helper_modules/token_counter/token_counter.py
black_langcube/helper_modules/token_counter/token_keys_sample.py
black_langcube/llm_modules/CheckTitleRelevance.py
black_langcube/llm_modules/__init__.py
black_langcube/llm_modules/check_tokens.py
black_langcube/llm_modules/llm_model.py
black_langcube-0.1.1.dist-info/licenses/LICENSE
black_langcube-0.1.1.dist-info/METADATA
black_langcube-0.1.1.dist-info/WHEEL
black_langcube-0.1.1.dist-info/top_level.txt
black_langcube-0.1.1.dist-info/RECORD
