Metadata-Version: 2.4
Name: black_langcube
Version: 0.1.1
Summary: A LangGraph-based extension framework for complex workflow applications, enabling the integration of various AI models and tools into a cohesive system.
Author-email: Martin Vanek <martin.vanek@cerna-kostka.cz>
License-Expression: MIT
Project-URL: Homepage, https://github.com/cerna-kostka/black-langcube
Project-URL: Repository, https://github.com/cerna-kostka/black-langcube
Project-URL: Documentation, https://github.com/cerna-kostka/black-langcube#readme
Project-URL: Issues, https://github.com/cerna-kostka/black-langcube/issues
Keywords: langgraph,workflow,llm,langchain,ai
Classifier: Development Status :: 4 - Beta
Classifier: Intended Audience :: Developers
Classifier: Programming Language :: Python :: 3
Classifier: Programming Language :: Python :: 3.9
Classifier: Programming Language :: Python :: 3.10
Classifier: Programming Language :: Python :: 3.11
Classifier: Programming Language :: Python :: 3.12
Classifier: Topic :: Software Development :: Libraries :: Python Modules
Classifier: Topic :: Scientific/Engineering :: Artificial Intelligence
Requires-Python: >=3.9
License-File: LICENSE
Requires-Dist: langchain>=0.3.24
Requires-Dist: langchain-core>=0.3.56
Requires-Dist: langchain-openai>=0.3.8
Requires-Dist: langchain-community>=0.3.23
Requires-Dist: langgraph>=0.3.7
Requires-Dist: langgraph-checkpoint>=2.0.18
Requires-Dist: langsmith>=0.3.13
Requires-Dist: pydantic<3.0.0,>=2.0.0
Requires-Dist: tiktoken>=0.9.0
Requires-Dist: typing-extensions>=4.12.2
Requires-Dist: openai
Requires-Dist: python-dotenv
Provides-Extra: dev
Requires-Dist: pytest>=7.0.0; extra == "dev"
Requires-Dist: pytest-cov; extra == "dev"
Requires-Dist: black; extra == "dev"
Requires-Dist: isort; extra == "dev"
Requires-Dist: flake8; extra == "dev"
Requires-Dist: mypy; extra == "dev"
Provides-Extra: examples
Requires-Dist: jupyter; extra == "examples"
Requires-Dist: notebook; extra == "examples"
Dynamic: license-file
